messysoup/__init__.py
messysoup/attributes.py
messysoup/messysoup.py
messysoup/pyodide/__init__.py
messysoup/pyodide/run_python.py
messysoup/pyodide/standard_library.json
messysoup/pyodide/supported_imports.json
messysoup/table/__init__.py
messysoup/table/table.py
messysoup/table/table_helpers.py
tests/__init__.py
tests/imports_test.py
tests/messysoup_test.py
tests/table_test.py
messysoup-0.0.3.dist-info/LICENSE
messysoup-0.0.3.dist-info/METADATA
messysoup-0.0.3.dist-info/WHEEL
messysoup-0.0.3.dist-info/top_level.txt
messysoup-0.0.3.dist-info/RECORD
