Metadata-Version: 2.1
Name: messysoup
Version: 0.0.3
Summary: A wrapper for html
Home-page: https://github.com/messysoup/messysoup
Author: messysoup
Author-email: messysoup@protonmail.com
License: MIT
Platform: UNKNOWN
Classifier: License :: OSI Approved :: MIT License
Classifier: Operating System :: OS Independent
Classifier: Programming Language :: Python :: 3
Classifier: Programming Language :: Python :: 3.7
Classifier: Programming Language :: Python :: 3.8
Classifier: Programming Language :: Python :: 3.9
Classifier: Programming Language :: Python :: 3.10
License-File: LICENSE
